ibb_veri_portali/__init__.py
ibb_veri_portali/ispark.py
ibb_veri_portali-0.2.0.dist-info/LICENCE
ibb_veri_portali-0.2.0.dist-info/METADATA
ibb_veri_portali-0.2.0.dist-info/WHEEL
ibb_veri_portali-0.2.0.dist-info/top_level.txt
ibb_veri_portali-0.2.0.dist-info/RECORD
