Metadata-Version: 2.1
Name: ibb_veri_portali
Version: 0.2.0
Summary: Ibb Portal
Home-page: https://github.com/yunusxxz
Author: yunusx
Author-email: isikyunusemre63@gmail.com
Classifier: Programming Language :: Python :: 3
Classifier: License :: OSI Approved :: MIT License
Classifier: Operating System :: OS Independent
Requires-Python: >=3.6
License-File: LICENCE
Requires-Dist: pandas
Requires-Dist: requests
